pageplanner_selenium/__init__.py
pageplanner_selenium/controls.js
pageplanner_selenium/pageplanner_selenium.py
pageplanner_selenium_benjihughes-0.14.dist-info/LICENSE
pageplanner_selenium_benjihughes-0.14.dist-info/METADATA
pageplanner_selenium_benjihughes-0.14.dist-info/WHEEL
pageplanner_selenium_benjihughes-0.14.dist-info/top_level.txt
pageplanner_selenium_benjihughes-0.14.dist-info/RECORD
