Metadata-Version: 2.1
Name: pageplanner-selenium-benjihughes
Version: 0.14
Summary: Offers a selenium interface to gather arguments for pageplanner.
Home-page: UNKNOWN
Author: Benji Hughes
Author-email: 
License: MIT
Platform: UNKNOWN
Classifier: License :: OSI Approved :: MIT License
Classifier: Programming Language :: Python
Classifier: Programming Language :: Python :: 3
Classifier: Programming Language :: Python :: 3.6
Classifier: Programming Language :: Python :: Implementation :: CPython
Classifier: Programming Language :: Python :: Implementation :: PyPy
Requires-Python: >=3.6.0
Requires-Dist: pageplanner-benjihughes
Requires-Dist: selenium
